cli/main.py
opends_cli-0.1.2.dist-info/LICENSE
opends_cli-0.1.2.dist-info/METADATA
opends_cli-0.1.2.dist-info/WHEEL
opends_cli-0.1.2.dist-info/entry_points.txt
opends_cli-0.1.2.dist-info/top_level.txt
opends_cli-0.1.2.dist-info/RECORD
