Metadata-Version: 2.1
Name: opends-cli
Version: 0.1.2
Summary: A command line client for running opendata.studio datakits
Author-email: Varvara Efremova <varvara@echus.co>, James Wilmot <jameswilmot2000@gmail.com>
Project-URL: Homepage, https://github.com/opendatastudio/cli
Project-URL: Bug Tracker, https://github.com/opendatastudio/cli/issues
Requires-Python: >=3.11
License-File: LICENSE
Requires-Dist: typer <1,>=0.12
Requires-Dist: docker <8,>=7.1.0
Requires-Dist: matplotlib <4,>=3.9.1
Requires-Dist: tornado
Requires-Dist: opendatapy >=0.1.2
Requires-Dist: tabulate
Provides-Extra: all
Requires-Dist: opends-cli[development] ; extra == 'all'
Provides-Extra: development
Requires-Dist: pre-commit ; extra == 'development'
Requires-Dist: build ; extra == 'development'
